RigolWFM/__init__.py
RigolWFM/channel.py
RigolWFM/wfm.py
RigolWFM/wfm1000b.py
RigolWFM/wfm1000c.py
RigolWFM/wfm1000d.py
RigolWFM/wfm1000e.py
RigolWFM/wfm1000z.py
RigolWFM/wfm2000.py
RigolWFM/wfm4000.py
RigolWFM/wfm6000.py
RigolWFM/wfmconvert.py
RigolWFM-1.0.0.dist-info/LICENSE.txt
RigolWFM-1.0.0.dist-info/METADATA
RigolWFM-1.0.0.dist-info/WHEEL
RigolWFM-1.0.0.dist-info/entry_points.txt
RigolWFM-1.0.0.dist-info/top_level.txt
RigolWFM-1.0.0.dist-info/RECORD
