Metadata-Version: 2.1
Name: RigolWFM
Version: 1.0.0
Summary: Read and parse Rigol Oscilloscope WFM files
Home-page: https://github.com/scottprahl/RigolWFM.git
Author: Scott Prahl
Author-email: scott.prahl@oit.edu
License: BSD 3-clause
Keywords: Rigol,wfm,DS1000B,DS1074B,DS1104B,DS1204B,DS1000C,DS1000CD,DS1000M,DS1000MD,DS1042C,DS1102CA,DS1202CA,DS1302CA,DS1062CA,DS1000D,DS1102D,DS1052D,DS1102D,DS1000E,DS1052E,DS1102E,DS1000Z,DS1054Z,MSO1054Z,DS1074Z,DS1074Z-S,MSO1074Z,DS1104Z,DS1104Z-S,MSO1104Z,DS1202Z,DS2000,DS2072A,DS2102A,MSO2102A,MSO2102A-S,DS2202A,MSO2202A,MSO2202A-S,DS2302A,MSO2302A,MSO2302A-S,DS4000,DS4012,MSO4012,DS4014,MSO4014,DS4022,MSO4022,DS4024,MSO4024,DS4032,MSO4032,DS4034,MSO4034,DS4052,MSO4052,DS4054,MSO4054,D
Classifier: Development Status :: 3 - Alpha
Classifier: License :: OSI Approved :: BSD License
Classifier: Intended Audience :: Science/Research
Classifier: Programming Language :: Python :: 3
Classifier: Programming Language :: Python :: 3.8
Classifier: Programming Language :: Python :: 3.9
Classifier: Programming Language :: Python :: 3.10
Classifier: Programming Language :: Python :: 3.11
Classifier: Topic :: Scientific/Engineering
Requires-Python: >=3.8
License-File: LICENSE.txt
Requires-Dist: kaitaistruct
Requires-Dist: numpy
Requires-Dist: matplotlib
Requires-Dist: requests
